forex_types/__init__.py
forex_types/calc.py
forex_types/cash.py
forex_types/currency.py
forex_types/direction.py
forex_types/frac_pips.py
forex_types/lot_size.py
forex_types/odd_math.py
forex_types/pair.py
forex_types/price.py
forex_types-0.0.7.dist-info/WHEEL
forex_types-0.0.7.dist-info/METADATA
forex_types-0.0.7.dist-info/RECORD
