Metadata-Version: 2.1
Name: forex-types
Version: 0.0.7
Summary: Basic Forex Classes
Home-page: https://github.com/aallaire/python_forex_types
License: MIT
Author: Andrew Allaire
Author-email: andrew.allaire@gmail.com
Requires-Python: >=3.5,<4.0
Classifier: License :: OSI Approved :: MIT License
Classifier: Programming Language :: Python :: 3
Classifier: Programming Language :: Python :: 3.5
Classifier: Programming Language :: Python :: 3.6
Classifier: Programming Language :: Python :: 3.7
Classifier: Programming Language :: Python :: 3.8
Project-URL: Repository, https://github.com/aallaire/python_forex_types
